sky_dictionary/__init__.py
sky_dictionary/admin.py
sky_dictionary/apps.py
sky_dictionary/models.py
sky_dictionary/service.py
sky_dictionary/urls.py
sky_dictionary/views.py
sky_dictionary-0.0.7.dist-info/METADATA
sky_dictionary-0.0.7.dist-info/WHEEL
sky_dictionary-0.0.7.dist-info/top_level.txt
sky_dictionary-0.0.7.dist-info/RECORD
