Metadata-Version: 2.1
Name: sky-dictionary
Version: 0.0.7
Summary: 字段配置模块
Home-page: UNKNOWN
Author: sunkaiyan
Author-email: sky4834@163.com
License: apache 3.0
Platform: UNKNOWN
Requires-Dist: django
Requires-Dist: django-simple-api
Requires-Dist: mysqlclient
